{
    "accounts": [
        {
            "id": "MT01",
            "name": "LUU SY TRUONG",
            "email": "lst@gmail.com",
            "password": "123"
        },
        {
            "id": "MT02",
            "name": "Lê Văn Tiến",
            "email": "tien@gmail.com",
            "password": "123"
        },
        {
            "id": "MT03",
            "name": "Nguyễn Thị Vân",
            "email": "van@gmail.com",
            "password": "123"
        },
        {
            "id": "MT04",
            "name": "Hoàng Anh Tú",
            "email": "tu@gmail.com",
            "password": "123"
        },
        {
            "id": "MT05",
            "name": "Ngô Gia Quyến",
            "email": "quyen@gmail.com",
            "password": "123"
        }
    ]
}